redvault/__init__.py
redvault/cli.py
redvault/redvault.py
redvault-0.1.0.dist-info/AUTHORS.rst
redvault-0.1.0.dist-info/LICENSE
redvault-0.1.0.dist-info/METADATA
redvault-0.1.0.dist-info/WHEEL
redvault-0.1.0.dist-info/entry_points.txt
redvault-0.1.0.dist-info/top_level.txt
redvault-0.1.0.dist-info/RECORD
