Metadata-Version: 2.1
Name: redvault
Version: 0.1.0
Summary: Distributed nearline backup system.
Home-page: https://github.com/ast0815/redvault
Author: Lukas Koch
Author-email: lukas.koch@mailbox.org
License: MIT license
Keywords: redvault
Platform: UNKNOWN
Classifier: Development Status :: 2 - Pre-Alpha
Classifier: Intended Audience :: Developers
Classifier: License :: OSI Approved :: MIT License
Classifier: Natural Language :: English
Classifier: Programming Language :: Python :: 3
Classifier: Programming Language :: Python :: 3.6
Classifier: Programming Language :: Python :: 3.7
Classifier: Programming Language :: Python :: 3.8
Requires-Python: >=3.6
License-File: LICENSE
License-File: AUTHORS.rst
Requires-Dist: Click (>=7.0)
